{
  "search": {
    "total": 15000,
    "business": [
      {
        "id": "4XX-zF8h5Lvrr22_tqU6-Q",
        "categories": [
          {
            "title": "New American"
          },
          {
            "title": "Wine Bars"
          },
          {
            "title": "Venues & Event Spaces"
          }
        ],
        "display_phone": "(718) 522-5200",
        "review_count": 1331,
        "reviews": [
          {
            "id": "8A4VEFuqlOrJeBYEvrikhQ",
            "rating": 5,
            "text": "Just first class amazing experience, great and different delicious wine pairings with food. \nService was efficient but not overwhelming. \nWhat can I say ......",
            "time_created": "2024-06-26 12:58:07",
            "user": {
              "id": "E03qg20wOvtDjqOPowzhjw",
              "image_url": "https://s3-media2.fl.yelpcdn.com/photo/T6RcdgIFleSm66fxlYfsgw/o.jpg",
              "name": "Joe H.",
              "profile_url": "https://www.yelp.com/user_details?userid=E03qg20wOvtDjqOPowzhjw"
            }
          },
          {
            "id": "fKTa9jiWU2WrRq-y2F77vg",
            "rating": 2,
            "text": "I'll leave two starts because I'm sure the food would have been great. \n\nTall brunette hostess working the evening of 11/5/23 - kindly just tell the...",
            "time_created": "2024-09-02 12:50:03",
            "user": {
              "id": "Ong2-gvzPGcoDMrJ8ZzcLg",
              "image_url": "https://s3-media3.fl.yelpcdn.com/photo/fsPnBTgIu6noS24IJ610JA/o.jpg",
              "name": "Christine M.",
              "profile_url": "https://www.yelp.com/user_details?userid=Ong2-gvzPGcoDMrJ8ZzcLg"
            }
          },
          {
            "id": "aVF7lIiy4YecsV5UgGnZXA",
            "rating": 5,
            "text": "Incredible service. Fantastic menu and view that can't be matched. Absolutely loved the specialty cocktails. This place is a gem. Don't forget your sports...",
            "time_created": "2024-08-29 13:02:22",
            "user": {
              "id": "Bb-w1iy4Qxpse-p42w9tzw",
              "image_url": "https://s3-media2.fl.yelpcdn.com/photo/eJA94CB0jPaD4nS4VkbN3g/o.jpg",
              "name": "Nikki P.",
              "profile_url": "https://www.yelp.com/user_details?userid=Bb-w1iy4Qxpse-p42w9tzw"
            }
          }
        ],
        "url": "https://www.yelp.com/biz/the-river-caf%C3%A9-brooklyn-3?adjust_creative=U9qLvU7mPOFxYgv7-mtcmA&utm_campaign=yelp_api_v3&utm_medium=api_v3_graphql&utm_source=U9qLvU7mPOFxYgv7-mtcmA",
        "rating": 4.1,
        "price": "$$$$",
        "photos": [
          "https://s3-media4.fl.yelpcdn.com/bphoto/djXq8DWf8bYE9rUC3tcsxA/o.jpg"
        ],
        "phone": "+17185225200",
        "name": "The River Café",
        "is_closed": false,
        "location": {
          "address1": "1 Water St",
          "address2": "",
          "address3": "",
          "city": "Brooklyn",
          "state": "NY",
          "postal_code": "11201",
          "country": "US"
        }
      },
      {
        "id": "liZmIO0FqZwslLJfLDkfgw",
        "categories": [
          {
            "title": "Thai"
          }
        ],
        "display_phone": "(212) 206-2500",
        "review_count": 709,
        "reviews": [
          {
            "id": "o0g6uvapSfTWpwiBmiHcTw",
            "rating": 5,
            "text": "Whenever I am in NY - I will always try to have a meal here.\nThe food is so good. I have yet to find a dish that was not delicious. \nPortions are also...",
            "time_created": "2024-07-07 06:35:14",
            "user": {
              "id": "drvon2Eg21Y_A49JFKPwmA",
              "image_url": "https://s3-media2.fl.yelpcdn.com/photo/h8rmAKWWrdKP7MeaQ6GVgQ/o.jpg",
              "name": "Tracy S.",
              "profile_url": "https://www.yelp.com/user_details?userid=drvon2Eg21Y_A49JFKPwmA"
            }
          },
          {
            "id": "LgQ0BL3mIz4h0bzyNk4LhA",
            "rating": 3,
            "text": "Not gonna lie - was a little disappointed with the food here.\n\nThe service was definitely nice, and the ambiance is cute (we were sat outside), but for a...",
            "time_created": "2024-08-20 18:21:57",
            "user": {
              "id": "f2ba-VDOpatAnuDef-KlKQ",
              "image_url": "https://s3-media2.fl.yelpcdn.com/photo/nohOaI-ta7QDkdAUtJJF6w/o.jpg",
              "name": "Andrew P.",
              "profile_url": "https://www.yelp.com/user_details?userid=f2ba-VDOpatAnuDef-KlKQ"
            }
          },
          {
            "id": "MV52aOd9coOu4ah325HGJA",
            "rating": 4,
            "text": "Best food I've had in years and I ordered TO-GO at that! The green beans with tofu is a sure fire bet. The fish and the desert were my favs. \n\nI definitely...",
            "time_created": "2024-06-10 11:03:32",
            "user": {
              "id": "ci-mepWGgsgGT3sFI2mhMg",
              "image_url": "https://s3-media4.fl.yelpcdn.com/photo/pOIhLwaqi8hJhrWlbvqIgA/o.jpg",
              "name": "M P.",
              "profile_url": "https://www.yelp.com/user_details?userid=ci-mepWGgsgGT3sFI2mhMg"
            }
          }
        ],
        "url": "https://www.yelp.com/biz/wayla-new-york?adjust_creative=U9qLvU7mPOFxYgv7-mtcmA&utm_campaign=yelp_api_v3&utm_medium=api_v3_graphql&utm_source=U9qLvU7mPOFxYgv7-mtcmA",
        "rating": 4.4,
        "price": "$$$",
        "photos": [
          "https://s3-media2.fl.yelpcdn.com/bphoto/u17PWWBYzqe3p1uEPgKVuQ/o.jpg"
        ],
        "phone": "+12122062500",
        "name": "Wayla",
        "is_closed": false,
        "location": {
          "address1": "100 Forsyth St",
          "address2": "Basement",
          "address3": null,
          "city": "New York",
          "state": "NY",
          "postal_code": "10002",
          "country": "US"
        }
      },
      {
        "id": "An1_BlhLJDZomxI91SBv7g",
        "categories": [
          {
            "title": "Korean"
          },
          {
            "title": "Bars"
          }
        ],
        "display_phone": "(212) 256-1259",
        "review_count": 302,
        "reviews": [
          {
            "id": "anXsgVOtT9IqeErWxxsJJQ",
            "rating": 5,
            "text": "Celebrated my birthday at Oiji Mi and had a great experience! Rip their previous spot Oiji (the honey butter chips...) but the same chef's work is alive and...",
            "time_created": "2024-09-11 09:31:31",
            "user": {
              "id": "HVQKFDi-vZbawtmLMq3ZOw",
              "image_url": "https://s3-media1.fl.yelpcdn.com/photo/fFkAFDONaC7ATEKs202brg/o.jpg",
              "name": "Gab G.",
              "profile_url": "https://www.yelp.com/user_details?userid=HVQKFDi-vZbawtmLMq3ZOw"
            }
          },
          {
            "id": "L-x6sfGJRq5T154MyRgA3A",
            "rating": 5,
            "text": "fantastic dinner. took my parents here to treat them to a nice dinner and i was a little nervous my traditional korean parents would be critical of a modern...",
            "time_created": "2024-09-06 10:38:30",
            "user": {
              "id": "taJ0LYP1Ttizr1-Dzpx0Wg",
              "image_url": "https://s3-media4.fl.yelpcdn.com/photo/0gtCNnVkPjDuywvSAdF67A/o.jpg",
              "name": "Jo L.",
              "profile_url": "https://www.yelp.com/user_details?userid=taJ0LYP1Ttizr1-Dzpx0Wg"
            }
          },
          {
            "id": "QcA-FklE02qfBR2hvbMW2Q",
            "rating": 5,
            "text": "Oiji Mi was such a delightful meal - we went for the tasting menu experience with 3-4 peoplel, which is how I recommend doing it if you can. With 4 people,...",
            "time_created": "2024-08-22 14:59:21",
            "user": {
              "id": "iEpB-JTCSgl8d8TPS4UAog",
              "image_url": "https://s3-media3.fl.yelpcdn.com/photo/m1oQpLcEraBCs_3Tn6z5Sw/o.jpg",
              "name": "Michelle G.",
              "profile_url": "https://www.yelp.com/user_details?userid=iEpB-JTCSgl8d8TPS4UAog"
            }
          }
        ],
        "url": "https://www.yelp.com/biz/oiji-mi-new-york-2?adjust_creative=U9qLvU7mPOFxYgv7-mtcmA&utm_campaign=yelp_api_v3&utm_medium=api_v3_graphql&utm_source=U9qLvU7mPOFxYgv7-mtcmA",
        "rating": 4.5,
        "price": "$$$$",
        "photos": [
          "https://s3-media3.fl.yelpcdn.com/bphoto/3Rc08rNDYtbijj-io4uayA/o.jpg"
        ],
        "phone": "+12122561259",
        "name": "Oiji Mi",
        "is_closed": true,
        "location": {
          "address1": "17 W 19th St",
          "address2": null,
          "address3": "",
          "city": "New York",
          "state": "NY",
          "postal_code": "10011",
          "country": "US"
        }
      },
      {
        "id": "s3jou_L_LVYGkNHiuhjlew",
        "categories": [
          {
            "title": "French"
          },
          {
            "title": "Cocktail Bars"
          },
          {
            "title": "Steakhouses"
          }
        ],
        "display_phone": "(212) 837-1616",
        "review_count": 2498,
        "reviews": [
          {
            "id": "FTYs7l3XtFfHFwRE_v7Gug",
            "rating": 4,
            "text": "phenomenal location & the service was fantastic!! perfect place to bring family who's visiting or for a girl's night",
            "time_created": "2024-08-23 17:27:54",
            "user": {
              "id": "sMlQbrxieHq8_DsPi5HmYA",
              "image_url": null,
              "name": "Natalie G.",
              "profile_url": "https://www.yelp.com/user_details?userid=sMlQbrxieHq8_DsPi5HmYA"
            }
          },
          {
            "id": "GM9pLNWHLmMyeNEiPF4Idw",
            "rating": 5,
            "text": "Alexandra was perfect with her service and food is amazing all around!  Will be back soon",
            "time_created": "2024-08-07 17:00:56",
            "user": {
              "id": "84CvTVpiXAAZDEl8YVVKUA",
              "image_url": null,
              "name": "Keane R.",
              "profile_url": "https://www.yelp.com/user_details?userid=84CvTVpiXAAZDEl8YVVKUA"
            }
          },
          {
            "id": "EOgeXnsV0R_L7LA81csqfQ",
            "rating": 5,
            "text": "Incredible food, drinks, atmosphere, and service. Alexandra had incredible recommendations and was very attentive! We loved sitting out on the patio, and...",
            "time_created": "2024-08-10 17:10:49",
            "user": {
              "id": "_ZXETKaYQUSSOJfoQrwphw",
              "image_url": null,
              "name": "Meg C.",
              "profile_url": "https://www.yelp.com/user_details?userid=_ZXETKaYQUSSOJfoQrwphw"
            }
          }
        ],
        "url": "https://www.yelp.com/biz/boucherie-west-village-new-york-3?adjust_creative=U9qLvU7mPOFxYgv7-mtcmA&utm_campaign=yelp_api_v3&utm_medium=api_v3_graphql&utm_source=U9qLvU7mPOFxYgv7-mtcmA",
        "rating": 4.5,
        "price": "$$$",
        "photos": [
          "https://s3-media1.fl.yelpcdn.com/bphoto/WxNMDkguiN5eVOOA9WEaog/o.jpg"
        ],
        "phone": "+12128371616",
        "name": "Boucherie West Village",
        "is_closed": false,
        "location": {
          "address1": "99 7th Ave S",
          "address2": "",
          "address3": null,
          "city": "New York",
          "state": "NY",
          "postal_code": "10014",
          "country": "US"
        }
      },
      {
        "id": "__EvomQ2tE1NtkWn32WEXg",
        "categories": [
          {
            "title": "Burgers"
          },
          {
            "title": "New American"
          },
          {
            "title": "Cocktail Bars"
          }
        ],
        "display_phone": "(646) 350-2429",
        "review_count": 1077,
        "reviews": [
          {
            "id": "G6B9W5ueFAIpc7ckNjZ1FA",
            "rating": 5,
            "text": "We had a GREAT time celebrating my daughter's birthday.\nEven though we didn't have a reservation, we didn't have to wait too long.\nThe food and the wine...",
            "time_created": "2024-09-11 14:32:11",
            "user": {
              "id": "Ig70eHxfHzwBjo9soQ4FAw",
              "image_url": "https://s3-media2.fl.yelpcdn.com/photo/lW9fZMsrpvR1O0w7t3ZU3g/o.jpg",
              "name": "Enrique C.",
              "profile_url": "https://www.yelp.com/user_details?userid=Ig70eHxfHzwBjo9soQ4FAw"
            }
          },
          {
            "id": "kmz0Xg_4l1oVrzX0BMJVYQ",
            "rating": 4,
            "text": "Yelp should really consider a 1/2 star rating. This place doesn't deserve a 5 but I hope 4 star is not too harsh. \nEverybody comes here for the burger...",
            "time_created": "2024-09-08 08:32:29",
            "user": {
              "id": "EErRt4UDcb4w9DTrdYgXjA",
              "image_url": "https://s3-media1.fl.yelpcdn.com/photo/Z2sUmq4VLEXM8FJBPu-03Q/o.jpg",
              "name": "Sam B.",
              "profile_url": "https://www.yelp.com/user_details?userid=EErRt4UDcb4w9DTrdYgXjA"
            }
          },
          {
            "id": "oLtBkYuD-_ljEenQ4yPW-Q",
            "rating": 4,
            "text": "I had been wanting to try Au Cheval for a while, after seeing photos of their famous burger with added bacon and egg. I came here at around noon on a...",
            "time_created": "2024-09-08 07:56:06",
            "user": {
              "id": "spq1tWgD3r81Twy6guM9Ag",
              "image_url": "https://s3-media4.fl.yelpcdn.com/photo/i9SrVcRfpaIqxpnles9qUg/o.jpg",
              "name": "Jasmine M.",
              "profile_url": "https://www.yelp.com/user_details?userid=spq1tWgD3r81Twy6guM9Ag"
            }
          }
        ],
        "url": "https://www.yelp.com/biz/au-cheval-new-york-7?adjust_creative=U9qLvU7mPOFxYgv7-mtcmA&utm_campaign=yelp_api_v3&utm_medium=api_v3_graphql&utm_source=U9qLvU7mPOFxYgv7-mtcmA",
        "rating": 4.3,
        "price": "$$$",
        "photos": [
          "https://s3-media3.fl.yelpcdn.com/bphoto/i3kwsfrNgtxP4L6nJE9lxQ/o.jpg"
        ],
        "phone": "+16463502429",
        "name": "Au Cheval",
        "is_closed": true,
        "location": {
          "address1": "33 Cortlandt Aly",
          "address2": "",
          "address3": null,
          "city": "New York",
          "state": "NY",
          "postal_code": "10013",
          "country": "US"
        }
      },
      {
        "id": "A_YpTLbAlEqeLVSs9bxbEA",
        "categories": [
          {
            "title": "Steakhouses"
          }
        ],
        "display_phone": "(212) 688-4190",
        "review_count": 3465,
        "reviews": [
          {
            "id": "gWuVPJ7caywP2nREEShxRw",
            "rating": 5,
            "text": "My boyfriend and I visited Bruno's Club A Steakhouse over the weekend and were beyond impressed. Not only was the food incredible, but the service was...",
            "time_created": "2024-08-13 09:05:18",
            "user": {
              "id": "gixuZQ5u_m6xIj8RFxYOQQ",
              "image_url": "https://s3-media1.fl.yelpcdn.com/photo/VigoQdh6JljizbPC00stwg/o.jpg",
              "name": "Abigail M.",
              "profile_url": "https://www.yelp.com/user_details?userid=gixuZQ5u_m6xIj8RFxYOQQ"
            }
          },
          {
            "id": "T2-OcKzlnzvU2XRFYjpwwg",
            "rating": 5,
            "text": "We celebrated our anniversary last week and we totally enjoyed the fine dining at Club A Steakhouse ... The owner Bruno & waitstaff Shaun were very friendly...",
            "time_created": "2024-08-04 15:57:10",
            "user": {
              "id": "GlqJ8Kokyf3wJ3b6cZ7SrA",
              "image_url": null,
              "name": "Margaret B.",
              "profile_url": "https://www.yelp.com/user_details?userid=GlqJ8Kokyf3wJ3b6cZ7SrA"
            }
          },
          {
            "id": "udtqSkm-W8IFDMmPoaB5VA",
            "rating": 5,
            "text": "Had my day-late birthday dinner at Club A on a Sunday evening.  First off, reservations were easy to make and easy to change.  Ambiance at Club A felt very...",
            "time_created": "2024-08-17 05:39:20",
            "user": {
              "id": "XjzFytXsJSQzcfa_gp4XTw",
              "image_url": "https://s3-media2.fl.yelpcdn.com/photo/N42xo5TQdCNQ8iv_Zh0FNA/o.jpg",
              "name": "David B.",
              "profile_url": "https://www.yelp.com/user_details?userid=XjzFytXsJSQzcfa_gp4XTw"
            }
          }
        ],
        "url": "https://www.yelp.com/biz/club-a-steakhouse-new-york?adjust_creative=U9qLvU7mPOFxYgv7-mtcmA&utm_campaign=yelp_api_v3&utm_medium=api_v3_graphql&utm_source=U9qLvU7mPOFxYgv7-mtcmA",
        "rating": 4.5,
        "price": "$$$",
        "photos": [
          "https://s3-media2.fl.yelpcdn.com/bphoto/L4WCds5RfdwOzlqRRJitcQ/o.jpg"
        ],
        "phone": "+12126884190",
        "name": "Club A Steakhouse",
        "is_closed": false,
        "location": {
          "address1": "240 E 58th St",
          "address2": "",
          "address3": "",
          "city": "New York",
          "state": "NY",
          "postal_code": "10022",
          "country": "US"
        }
      },
      {
        "id": "klAhw3xLQi9GF1tf_HnS7w",
        "categories": [
          {
            "title": "Tapas Bars"
          },
          {
            "title": "Sushi Bars"
          },
          {
            "title": "Izakaya"
          }
        ],
        "display_phone": "(646) 368-9384",
        "review_count": 3067,
        "reviews": [
          {
            "id": "0KIpZnXjc4z-fzMMfIQZ_g",
            "rating": 5,
            "text": "Bookmarked forever, we finally had a happy opportunity to check this place out. \n\nChecked the 'Tips' where some encouraged just show up and wait or if...",
            "time_created": "2024-09-07 06:16:42",
            "user": {
              "id": "1k2ilG84PtPAm9cP_EQHjQ",
              "image_url": "https://s3-media3.fl.yelpcdn.com/photo/q_7AD6sSODhv11r0yPYLzA/o.jpg",
              "name": "Pat F.",
              "profile_url": "https://www.yelp.com/user_details?userid=1k2ilG84PtPAm9cP_EQHjQ"
            }
          },
          {
            "id": "kQrxVw239kE6h4-YuCF2DA",
            "rating": 4,
            "text": "Wow this place is poppin'. We put our name down for a party of 2 and waited around 45-1 hour. We did some shopping at urban outfitters while we waited for...",
            "time_created": "2024-09-13 19:22:40",
            "user": {
              "id": "WT4Y6Ji7LdY8TfjvmzU-EA",
              "image_url": "https://s3-media4.fl.yelpcdn.com/photo/mqEpKA3YPCSi2c2kJQJXpQ/o.jpg",
              "name": "Rae A.",
              "profile_url": "https://www.yelp.com/user_details?userid=WT4Y6Ji7LdY8TfjvmzU-EA"
            }
          },
          {
            "id": "mEKLSiVuwc-JpJhW97lR_A",
            "rating": 5,
            "text": "Came in with high expectations and it did not disappoint :) Chicken nanban was super tender and juicy, and the egg salad on top was soo good. I think I...",
            "time_created": "2024-09-04 23:51:47",
            "user": {
              "id": "LHs-csmCAXOpyP11jFjwng",
              "image_url": "https://s3-media4.fl.yelpcdn.com/photo/cBu-B6Z6u_rHWqmTF5mqeg/o.jpg",
              "name": "Michelle F.",
              "profile_url": "https://www.yelp.com/user_details?userid=LHs-csmCAXOpyP11jFjwng"
            }
          }
        ],
        "url": "https://www.yelp.com/biz/izakaya-mew-new-york-3?adjust_creative=U9qLvU7mPOFxYgv7-mtcmA&utm_campaign=yelp_api_v3&utm_medium=api_v3_graphql&utm_source=U9qLvU7mPOFxYgv7-mtcmA",
        "rating": 4.3,
        "price": "$$",
        "photos": [
          "https://s3-media4.fl.yelpcdn.com/bphoto/-56mpvzUi0nfYADw2uQXhg/o.jpg"
        ],
        "phone": "+16463689384",
        "name": "Izakaya MEW",
        "is_closed": false,
        "location": {
          "address1": "53 W 35th St",
          "address2": "",
          "address3": "",
          "city": "New York",
          "state": "NY",
          "postal_code": "10001",
          "country": "US"
        }
      },
      {
        "id": "Er9SlDRdxit2qVHwfg-lsw",
        "categories": [
          {
            "title": "Caribbean"
          },
          {
            "title": "African"
          }
        ],
        "display_phone": "(212) 875-5222",
        "review_count": 391,
        "reviews": [
          {
            "id": "A1PECwrASyQ7DKSQ-EqsXQ",
            "rating": 5,
            "text": "Tatiana by Kwame Onwuachi was fire hit after fire hit. The ambiance was really nice, even when you take yourself on a solo date. The restroom was pretty...",
            "time_created": "2024-08-16 16:04:32",
            "user": {
              "id": "WUF1exWhBYX6ruuQTTuZ1w",
              "image_url": null,
              "name": "Al V.",
              "profile_url": "https://www.yelp.com/user_details?userid=WUF1exWhBYX6ruuQTTuZ1w"
            }
          },
          {
            "id": "O1Poy3jVXrgFOoHXvyKtwA",
            "rating": 5,
            "text": "Had the pleasure of dining at this wonderful restaurant on our vacation with my cousin.  It was a Tuesday night but inside it felt like a Saturday evening....",
            "time_created": "2024-08-19 19:00:05",
            "user": {
              "id": "hBxJwHZ495kzTwJxoeGyPA",
              "image_url": null,
              "name": "Monique H.",
              "profile_url": "https://www.yelp.com/user_details?userid=hBxJwHZ495kzTwJxoeGyPA"
            }
          },
          {
            "id": "d2x9IhGZ2wtlQtG9o3JKuw",
            "rating": 5,
            "text": "Tatiana has a Michelin star for a reason. I can confidently say that this was one of the best meals I've ever had in my entire life. \n\nI still think about...",
            "time_created": "2024-08-31 16:40:34",
            "user": {
              "id": "cd5OK4LxwyVWfY6UuDOQsg",
              "image_url": "https://s3-media3.fl.yelpcdn.com/photo/hRLH8BuvmDNCR43KudIvcA/o.jpg",
              "name": "Jennifer S.",
              "profile_url": "https://www.yelp.com/user_details?userid=cd5OK4LxwyVWfY6UuDOQsg"
            }
          }
        ],
        "url": "https://www.yelp.com/biz/tatiana-by-kwame-onwuachi-new-york-3?adjust_creative=U9qLvU7mPOFxYgv7-mtcmA&utm_campaign=yelp_api_v3&utm_medium=api_v3_graphql&utm_source=U9qLvU7mPOFxYgv7-mtcmA",
        "rating": 4.4,
        "price": "$$$$",
        "photos": [
          "https://s3-media3.fl.yelpcdn.com/bphoto/Guo8PDf2oTOlTiUYUJLEzA/o.jpg"
        ],
        "phone": "+12128755222",
        "name": "Tatiana By Kwame Onwuachi",
        "is_closed": false,
        "location": {
          "address1": "10 Lincoln Center Plz",
          "address2": "",
          "address3": null,
          "city": "New York",
          "state": "NY",
          "postal_code": "10023",
          "country": "US"
        }
      },
      {
        "id": "wGFSTTB6b4MHJJUzBnVJeg",
        "categories": [
          {
            "title": "Thai"
          },
          {
            "title": "Cocktail Bars"
          },
          {
            "title": "Halal"
          }
        ],
        "display_phone": "(646) 726-4418",
        "review_count": 2052,
        "reviews": [
          {
            "id": "2M9g4BiAF12KoMU6cE690w",
            "rating": 5,
            "text": "Great location, ambiance, and service!! First time trying Thai Food, excited to try the Mango Sticky Rice!",
            "time_created": "2024-08-30 16:29:00",
            "user": {
              "id": "tt8mR-Na2BWVRUDANQWQiQ",
              "image_url": "https://s3-media1.fl.yelpcdn.com/photo/vZYFL8e6EuY7D_sNzkPF6A/o.jpg",
              "name": "Camila",
              "profile_url": "https://www.yelp.com/user_details?userid=tt8mR-Na2BWVRUDANQWQiQ"
            }
          },
          {
            "id": "Kdf1by-QM332YH_sWNkR2g",
            "rating": 4,
            "text": "Cute Thai restaurant located near NYU. I had their Shrimp Pad Thai and Springrolls. I reall liked the Springrolls which were meaty and crispy. The Pad thai...",
            "time_created": "2024-08-16 08:56:47",
            "user": {
              "id": "AJ8jMRbsJxt77b3QVzt7Jw",
              "image_url": null,
              "name": "Yehee L.",
              "profile_url": "https://www.yelp.com/user_details?userid=AJ8jMRbsJxt77b3QVzt7Jw"
            }
          },
          {
            "id": "RqEZUd3iHUvtaMIm4IEViQ",
            "rating": 5,
            "text": "Came with friends and they had good food and ambience! They are very nice and service was a 10/10!!",
            "time_created": "2024-08-30 16:30:10",
            "user": {
              "id": "C0eOpnsbz_FYjMzCVf7fJQ",
              "image_url": null,
              "name": "Emily 2.",
              "profile_url": "https://www.yelp.com/user_details?userid=C0eOpnsbz_FYjMzCVf7fJQ"
            }
          }
        ],
        "url": "https://www.yelp.com/biz/top-thai-greenwich-new-york?adjust_creative=U9qLvU7mPOFxYgv7-mtcmA&utm_campaign=yelp_api_v3&utm_medium=api_v3_graphql&utm_source=U9qLvU7mPOFxYgv7-mtcmA",
        "rating": 4.4,
        "price": "$$",
        "photos": [
          "https://s3-media3.fl.yelpcdn.com/bphoto/4Hg5Af7A2RGpkDdDNLD9cg/o.jpg"
        ],
        "phone": "+16467264418",
        "name": "Top Thai Greenwich",
        "is_closed": false,
        "location": {
          "address1": "235 Sullivan St",
          "address2": "",
          "address3": null,
          "city": "New York",
          "state": "NY",
          "postal_code": "10012",
          "country": "US"
        }
      },
      {
        "id": "nMyot99PkX5iYCdxHoRJqQ",
        "categories": [
          {
            "title": "Korean"
          },
          {
            "title": "Tapas/Small Plates"
          },
          {
            "title": "Gastropubs"
          }
        ],
        "display_phone": "(646) 422-7466",
        "review_count": 318,
        "reviews": [
          {
            "id": "P3vu4WOdLMq9sqxYipm2Sg",
            "rating": 5,
            "text": "I really enjoyed this meal! 8 dishes was a perfect amount for 4 people for us - we probably could've gone with 7 but everything looked (and ended being) so...",
            "time_created": "2024-08-23 18:01:16",
            "user": {
              "id": "r2ES4hClsS5TkQdCcp5ZQw",
              "image_url": "https://s3-media3.fl.yelpcdn.com/photo/I2lvgsnQq6Rzeis0hKn0HA/o.jpg",
              "name": "Jennie B.",
              "profile_url": "https://www.yelp.com/user_details?userid=r2ES4hClsS5TkQdCcp5ZQw"
            }
          },
          {
            "id": "MBL8OivY32aLM-hJgmFntw",
            "rating": 4,
            "text": "My visit to ARIARI is part of my ongoing exploration of Hand Hospitality's restaurant portfolio. I visited when they first opened last year, and they've...",
            "time_created": "2024-08-09 11:53:28",
            "user": {
              "id": "VLTBPUrbNRR-f84h-altQw",
              "image_url": "https://s3-media2.fl.yelpcdn.com/photo/A1NK2p0-9_nQX_SETgIlKA/o.jpg",
              "name": "Morlene C.",
              "profile_url": "https://www.yelp.com/user_details?userid=VLTBPUrbNRR-f84h-altQw"
            }
          },
          {
            "id": "ygCG5BZCu6mFgIFSjo1xFg",
            "rating": 5,
            "text": "I came here with a party of 3 for an early dinner . Be sure to make a reservation because the place got packed very quickly! There are generally tables of 2...",
            "time_created": "2024-08-06 08:47:40",
            "user": {
              "id": "MvfaaDxHvdk5z2eD6D-KXg",
              "image_url": "https://s3-media4.fl.yelpcdn.com/photo/nWGrrkFVrf3qKaWvdq5IAQ/o.jpg",
              "name": "Anita J.",
              "profile_url": "https://www.yelp.com/user_details?userid=MvfaaDxHvdk5z2eD6D-KXg"
            }
          }
        ],
        "url": "https://www.yelp.com/biz/ariari-new-york?adjust_creative=U9qLvU7mPOFxYgv7-mtcmA&utm_campaign=yelp_api_v3&utm_medium=api_v3_graphql&utm_source=U9qLvU7mPOFxYgv7-mtcmA",
        "rating": 4.4,
        "price": null,
        "photos": [
          "https://s3-media1.fl.yelpcdn.com/bphoto/IQbVjJaYnvf1QZlgocL1Bw/o.jpg"
        ],
        "phone": "+16464227466",
        "name": "ARIARI",
        "is_closed": false,
        "location": {
          "address1": "119 1st Ave",
          "address2": null,
          "address3": "",
          "city": "New York",
          "state": "NY",
          "postal_code": "10003",
          "country": "US"
        }
      }
    ]
  }
}